dajax/__init__.py
dajax/core.py
dajax/models.py
dajax/static/dajax/dojo.dajax.core.js
dajax/static/dajax/jquery.dajax.core.js
dajax/static/dajax/mootools.dajax.core.js
dajax/static/dajax/prototype.dajax.core.js
django_dajax3-0.9.3.dist-info/AUTHORS
django_dajax3-0.9.3.dist-info/COPYING
django_dajax3-0.9.3.dist-info/METADATA
django_dajax3-0.9.3.dist-info/WHEEL
django_dajax3-0.9.3.dist-info/top_level.txt
django_dajax3-0.9.3.dist-info/RECORD
